genheader/__init__.py
genheader/__main__.py
genheader/_version.py
genheader/injector/__init__.py
genheader/injector/headers.py
genheader/proto/__init__.py
genheader/proto/protos.py
genheader/proto/sources.py
genheader/utils/__init__.py
genheader/utils/arg_parsing.py
genheader/utils/colors.py
genheader/utils/regexrules.py
genheader/utils/utils.py
genheader-1.1.2.dist-info/LICENSE
genheader-1.1.2.dist-info/METADATA
genheader-1.1.2.dist-info/WHEEL
genheader-1.1.2.dist-info/entry_points.txt
genheader-1.1.2.dist-info/top_level.txt
genheader-1.1.2.dist-info/RECORD
