Metadata-Version: 2.1
Name: genheader
Version: 1.1.2
Summary: A tool to inject prototypes into header from C files.
Home-page: https://github.com/maplepy/genheader
Author: maplepy
Author-email: your-email@example.com
Classifier: Programming Language :: Python :: 3
Classifier: License :: OSI Approved :: MIT License
Classifier: Operating System :: OS Independent
Classifier: Development Status :: 3 - Alpha
Requires-Python: >=3.8.2
License-File: LICENSE
